---
layout:     article
categories: [java]
title:      Java枚举
tags:       [java, 枚举]
date:       2016-03-06
---

> `枚举`是jdk1.5引入的新特性，本质上是一个特殊的类。

#### 枚举定义

首先，我们来定义一个枚举。

```java
public enum Color {

    RED, GREEN, BLUE;
    
}
```

然后，我们就可以按照常量的方式来使用枚举，例如`Color.RED`、`Color.GREEN`、`Color.BLUE`，在实际开发中，我们可以使用枚举来替代常量。

#### 枚举中定义实例变量

枚举中可以定义实例变量，同时，一般要定义相应的构造函数来初始化实例变量。

```java
public enum Color {

    RED("red"), GREEN("green"), BLUE("blue");

    Color(String rgb) {
        this.rgb = rgb;
    }

    private String rgb;

}
```

> `注：`枚举的构造函数必须是`private`或`friendly`，以防在代码中直接实例化枚举。

#### 枚举中定义抽象方法

枚举中可以定义抽象方法。

```java
public enum Color {

    RED {
        @Override
        public String getName() {
            return "red";
        }
    },

    GREEN {
        @Override
        public String getName() {
            return "green";
        }
    },

    BLUE {
        @Override
        public String getName() {
            return "blud";
        }
    };

    public abstract String getName();

}
```

#### 枚举实现接口

枚举可以实现一个或多个接口。

```java
public interface RGB {

    public String getRGB();

}

public enum Color implements RGB {

    RED(255, 0, 0), GREEN(0, 255, 0), BLUE(0, 0, 255);

    Color(int r, int g, int b) {
        this.r = r;
        this.g = g;
        this.b = b;
    }

    private int r;
    private int g;
    private int b;

    @Override
    public String getRGB() {
        return "rgb(" + r + "," + g + "," + b + ")";
    }

}
```

> `注：`枚举不可以继承，原因下面再说。

#### 枚举支持switch

在switch中可以使用枚举。

```java
public static void switchColor(Color color) {
    switch (color) {
        case RED:
            System.out.println("color red");
            break;
        case GREEN:
            System.out.println("color green");
            break;
        case Blue:
            System.out.println("color blue");
            break;
        default:
            System.out.println("no color");
            break;
    }
}
```

以上就是枚举的常见用法，下面来给大家讲解一下枚举的实现原理。

#### 枚举的原理

可能大部分同学对枚举的常见用法都很熟悉，但对枚举的实现原理可能就不了解了。

枚举是`Java`的一个`语法糖`，是`JVM`在编译生成`字节码`的时候生成的，先来看下枚举`反编译`后是什么样子。

```javap -p Color.class```

```java
public final class Color extends java.lang.Enum<Color> {
  public static final Color RED;
  public static final Color GREEN;
  public static final Color BLUE;
  private static final Color[] $VALUES;
  public static Color[] values();
  public static Color valueOf(java.lang.String);
  private Color();
  static {};
}
```

```javap -c Color.class```

```java
public final class Color extends java.lang.Enum<Color> {
  public static final Color RED;

  public static final Color GREEN;

  public static final Color BLUE;

  public static Color[] values();
    Code:
       0: getstatic     #1                  // Field $VALUES:[LColor;
       3: invokevirtual #2                  // Method "[LColor;".clone:()Ljava/lang/Object;
       6: checkcast     #3                  // class "[LColor;"
       9: areturn

  public static Color valueOf(java.lang.String);
    Code:
       0: ldc           #4                  // class Color
       2: aload_0
       3: invokestatic  #5                  // Method java/lang/Enum.valueOf:(Ljava/lang/Class;Ljava/lang/String;)Ljava/lang/Enum;
       6: checkcast     #4                  // class Color
       9: areturn

  static {};
    Code:
       0: new           #4                  // class Color
       3: dup
       4: ldc           #7                  // String RED
       6: iconst_0
       7: invokespecial #8                  // Method "<init>":(Ljava/lang/String;I)V
      10: putstatic     #9                  // Field RED:LColor;
      13: new           #4                  // class Color
      16: dup
      17: ldc           #10                 // String GREEN
      19: iconst_1
      20: invokespecial #8                  // Method "<init>":(Ljava/lang/String;I)V
      23: putstatic     #11                 // Field GREEN:LColor;
      26: new           #4                  // class Color
      29: dup
      30: ldc           #12                 // String BLUE
      32: iconst_2
      33: invokespecial #8                  // Method "<init>":(Ljava/lang/String;I)V
      36: putstatic     #13                 // Field BLUE:LColor;
      39: iconst_3
      40: anewarray     #4                  // class Color
      43: dup
      44: iconst_0
      45: getstatic     #9                  // Field RED:LColor;
      48: aastore
      49: dup
      50: iconst_1
      51: getstatic     #11                 // Field GREEN:LColor;
      54: aastore
      55: dup
      56: iconst_2
      57: getstatic     #13                 // Field BLUE:LColor;
      60: aastore
      61: putstatic     #1                  // Field $VALUES:[LColor;
      64: return
}
```

还原为Java代码后大致是下面这样子

```java
public final class Color extends java.lang.Enum<Color> {

    public static final Color RED;
    public static final Color GREEN;
    public static final Color BLUE;
    private static Color[] $VALUES;

    static {
        RED = new Color("RED", 0);
        GREEN = new Color("GREEN", 1);
        BLUE = new Color("BLUE", 2);
        $VALUES = (new Color[]{RED, GREEN, BLUE});
    }

    private Color(String name, int ordinal) {
        super(name, ordinal);
    }

    public static Color[] values() {
        return $VALUES.clone();
    }

    public static Color valueOf(String name) {
        return Enum.valueOf(Color.class, name);
    }

}
```

从这个代码中可以看出以下几点：

* 枚举是`final`类型的，不可被继承
* 枚举都是继承自`java.lang.Enum`
* 枚举常量本质上是`static final`的类常量，因此可以通过`Color.RED`直接使用
* 枚举中有一个`static`的枚举类型数组，按顺序存放所有的枚举常量
* 枚举提供了`values()`和`valueOf()`两个`static`方法，分别用来获取枚举数组和按照名称获取枚举

既然枚举是继承自`java.lang.Enum`，下面来看下`java.lang.Enum`的源码。

```java
public abstract class Enum<E extends Enum<E>> implements Comparable<E>, Serializable {

    // 枚举名称
    private final String name;

    // 枚举位置
    private final int ordinal;

    // 构造方法子类必须实现
    protected Enum(String name, int ordinal) {
        this.name = name;
        this.ordinal = ordinal;
    }

    public final String name() {
        return name;
    }

    public final int ordinal() {
        return ordinal;
    }

    public final int hashCode() {
        return super.hashCode();
    }

    public final boolean equals(Object other) {
        return this == other;
    }

    public String toString() {
        return name;
    }

    // 阻止枚举的克隆
    protected final Object clone() throws CloneNotSupportedException {
        throw new CloneNotSupportedException();
    }

    // 先判断是否同一个class,然后比较ordinal
    public final int compareTo(E o) {
        Enum<?> other = (Enum<?>) o;
        Enum<E> self = this;
        if (self.getClass() != other.getClass() && self.getDeclaringClass() != other.getDeclaringClass())
            throw new ClassCastException();
        return self.ordinal - other.ordinal;
    }

    // 获取枚举
    public static <T extends Enum<T>> T valueOf(Class<T> enumType, String name) {
        T result = enumType.enumConstantDirectory().get(name);
        if (result != null)
            return result;
        if (name == null)
            throw new NullPointerException("Name is null");
        throw new IllegalArgumentException(
                "No enum constant " + enumType.getCanonicalName() + "." + name);
    }

    // 阻止默认的反序列护化
    private void readObject(ObjectInputStream in) throws IOException,
            ClassNotFoundException {
        throw new InvalidObjectException("can't deserialize enum");
    }

    // 阻止默认的反序列护化
    private void readObjectNoData() throws ObjectStreamException {
        throw new InvalidObjectException("can't deserialize enum");
    }

}
```

我们可以看出

* `java.lang.Enum`实现了`Comparable`和`Serializable`接口
* `java.lang.Enum`都有`name`和`ordinal`两个`private`属性，可以通过`getName()`和`getOrdinal()`获取
* `java.lang.Enum`只提供了一个构造函数，因此子类必须实现
* `java.lang.Enum`重写了`hashCode()`、`equals()`、`clone()`方法并声明为`final`类型，子类枚举不可覆盖

#### 枚举序列化/反序列化的问题

因为枚举是由`name`属性唯一标识的,所以只序列化`name`属性就可以了,然后根据`name`属性来反序列化.实际上,jdk提供的序列化和反序列化也是这样实现的.

```java
if (obj instanceof Enum) {
    writeEnum((Enum<?>) obj, desc, unshared);
}
```

```java
private void writeEnum(Enum<?> en, ObjectStreamClass desc, boolean unshared) throws IOException {
    // 写入枚举的标识
    bout.writeByte(TC_ENUM);
    ObjectStreamClass sdesc = desc.getSuperDesc();
    // 写入class描述
    writeClassDesc((sdesc.forClass() == Enum.class) ? desc : sdesc, false);
    handles.assign(unshared ? null : en);
    // 写入枚举的name属性
    writeString(en.name(), false);
}
```

`ObjectInputStream`中的`readEnum()`方法就是枚举反序列化的过程

```java
private void writeEnum(Enum<?> en, ObjectStreamClass desc, boolean unshared) throws IOException {
    // 读取class描述
    ObjectStreamClass desc = readClassDesc(false);
    // 读取name属性
    String name = readString(false);
    Enum<?> result = null;
    // class描述转化为class
    Class<?> cl = desc.forClass();
    if (cl != null) {
        try {
            // 获取枚举值
            Enum<?> en = Enum.valueOf((Class) cl, name);
            result = en;
        } catch (IllegalArgumentException ex) {
        }
    }
}
```
